ocr/__init__.py
ocr/config.py
ocr/main.py
python_ocr-0.1.5.dist-info/LICENSE
python_ocr-0.1.5.dist-info/METADATA
python_ocr-0.1.5.dist-info/WHEEL
python_ocr-0.1.5.dist-info/top_level.txt
python_ocr-0.1.5.dist-info/RECORD
