Metadata-Version: 2.1
Name: python-ocr
Version: 0.1.5
Summary: Input Adaptor to verify file extension
Author: Crossml
Author-email: amar@crossml.com
License: MIT
Keywords: ocr,tesseract,easyocr,imgaeprocessing
Platform: UNKNOWN
Requires-Python: >=3
License-File: LICENSE
Requires-Dist: pytesseract
Requires-Dist: pdf2image
Requires-Dist: boto3
Requires-Dist: easyocr
